orionx_python_client/__init__.py
orionx_python_client/async_client/api.py
orionx_python_client/async_client/orders.py
orionx_python_client/async_client/token.py
orionx_python_client/async_client/trade_history.py
orionx_python_client/client/api.py
orionx_python_client/client/orders.py
orionx_python_client/client/token.py
orionx_python_client/client/trade_history.py
orionx_python_client/currency.py
orionx_python_client/queries.py
orionx_python_client-0.4.2.dist-info/WHEEL
orionx_python_client-0.4.2.dist-info/METADATA
orionx_python_client-0.4.2.dist-info/RECORD
